text_data/__init__.py
text_data/core/__init__.py
text_data/display.py
text_data/index.py
text_data/multi_corpus.py
text_data/query.py
text_data/tokenize.py
text_data-0.1.0.dist-info/LICENSE
text_data-0.1.0.dist-info/WHEEL
text_data-0.1.0.dist-info/METADATA
text_data-0.1.0.dist-info/RECORD
