Metadata-Version: 2.1
Name: text-data
Version: 0.1.0
Summary: A Python package for exploring text data for analysis
Home-page: https://github.com/maxblee/text_data
License: MIT
Keywords: text data,data exploration
Author: Max Lee
Author-email: maxbmhlee@gmail.com
Requires-Python: >=3.7,<4.0
Classifier: License :: OSI Approved :: MIT License
Classifier: Operating System :: OS Independent
Classifier: Programming Language :: Python :: 3
Classifier: Programming Language :: Python :: 3.6
Classifier: Programming Language :: Python :: 3.7
Classifier: Programming Language :: Python :: 3.8
Classifier: Programming Language :: Python :: 3.9
Classifier: Programming Language :: Rust
Provides-Extra: display
Requires-Dist: altair (>=4.1.0,<5.0.0); extra == "display"
Requires-Dist: ipython
Requires-Dist: numpy
Requires-Dist: pandas; extra == "display"
Requires-Dist: text_data_rs (>=0.1.0,<0.2.0)
Project-URL: Documentation, https://maxblee.github.io/apis/text_data/
Project-URL: Repository, https://github.com/maxblee/text_data
